{
  "version": "wiggler-runtime-prob-grid-v1",
  "asset": "DOGE",
  "market_type": "up_down",
  "interval_sec": 300,
  "anchor_mode": "boundary",
  "generated_at_iso": "2026-04-30T18:14:29Z",
  "source": {
    "config_hash": "7df9b01554ff8cf70de1aace3bc0ecf24b8539039a18026bba04b5ff593b267d",
    "training_input_hash": "426007710a81871dedc3f0867c843f854293d0ab367f8494c464659ce9c53ead",
    "wiggler_data_git_commit_sha": "6fcaf5fa5b2907d7b53cbd117899eb755a09af05",
    "wiggler_data_git_dirty": true,
    "source_generated_at_iso": "2026-04-30T17:45:40.021Z"
  },
  "training": {
    "label_source": "vwap",
    "label_source_kind": "vwap_chainlink_proxy",
    "label_source_note": "wiggler-data cross-source 1m VWAP across coinbase, binance, bitstamp. Used as a Chainlink proxy: at training time we have no historical Chainlink data, so basis risk versus the live resolution feed is unmeasured.",
    "rowcount": 420412,
    "window_start_ms": 1746030120000,
    "window_end_ms": 1777562820000
  },
  "resolution_source": {
    "intended": {
      "name": "Chainlink Data Streams",
      "symbol": "DOGE/USD"
    },
    "proxy_basis_risk": "unmeasured"
  },
  "abs_d_bps_boundaries": [
    0,
    2,
    4,
    6,
    8,
    10,
    15,
    20,
    25,
    30,
    40,
    50,
    75
  ],
  "remaining_sec_buckets": [
    60,
    120,
    180,
    240
  ],
  "vol_bins": {
    "method": "training_terciles_with_p90_tail",
    "thresholds_bps_per_sqrt_min": {
      "lowMaxBpsPerSqrtMin": 5.522680508593631,
      "normalMaxBpsPerSqrtMin": 8.48331696134635,
      "highMaxBpsPerSqrtMin": 13.629624597422582
    },
    "vol_lookback_min": 30
  },
  "fee": {
    "formula": "fee = shares * fee_rate * price * (1 - price)",
    "taker_fee_rate": 0.072
  },
  "risk_defaults": {
    "min_remaining_sec_to_trade": 60,
    "min_edge_probability": 0.015,
    "max_position_usdc": 250,
    "kelly_fraction": 0.1,
    "max_position_note": "Suggested per-market cap from research config; production may override downward but should not exceed without explicit operator change."
  },
  "lookup_rules": {
    "use_probability": "p_win_lower",
    "valid_side_leading_values": [
      "up_leading",
      "down_leading"
    ],
    "at_line_policy": "no_trade",
    "distance_bucket_rule": "abs_d_bps_min <= abs(d_bps) < abs_d_bps_max; null max means open-ended",
    "remaining_bucket_rule": "use the smallest configured remaining_sec bucket >= actual remaining seconds; if actual remaining seconds < min_remaining_sec_to_trade, no trade"
  },
  "cells": [
    {
      "remaining_sec": 60,
      "vol_bin": "low",
      "side_leading": "up_leading",
      "abs_d_bps_min": 0,
      "abs_d_bps_max": 2,
      "sample_count": 1600,
      "wins": 947,
      "p_win": 0.591875,
      "p_win_lower": 0.571525
    },
    {
      "remaining_sec": 60,
      "vol_bin": "low",
      "side_leading": "up_leading",
      "abs_d_bps_min": 2,
      "abs_d_bps_max": 4,
      "sample_count": 2947,
      "wins": 2251,
      "p_win": 0.763828,
      "p_win_lower": 0.75072
    },
    {
      "remaining_sec": 60,
      "vol_bin": "low",
      "side_leading": "up_leading",
      "abs_d_bps_min": 4,
      "abs_d_bps_max": 6,
      "sample_count": 2682,
      "wins": 2320,
      "p_win": 0.865026,
      "p_win_lower": 0.853804
    },
    {
      "remaining_sec": 60,
      "vol_bin": "low",
      "side_leading": "up_leading",
      "abs_d_bps_min": 6,
      "abs_d_bps_max": 8,
      "sample_count": 2187,
      "wins": 2055,
      "p_win": 0.939643,
      "p_win_lower": 0.930711
    },
    {
      "remaining_sec": 60,
      "vol_bin": "low",
      "side_leading": "up_leading",
      "abs_d_bps_min": 8,
      "abs_d_bps_max": 10,
      "sample_count": 1769,
      "wins": 1712,
      "p_win": 0.967778,
      "p_win_lower": 0.960126
    },
    {
      "remaining_sec": 60,
      "vol_bin": "low",
      "side_leading": "up_leading",
      "abs_d_bps_min": 10,
      "abs_d_bps_max": 15,
      "sample_count": 2771,
      "wins": 2725,
      "p_win": 0.983399,
      "p_win_lower": 0.97891
    },
    {
      "remaining_sec": 60,
      "vol_bin": "low",
      "side_leading": "up_leading",
      "abs_d_bps_min": 15,
      "abs_d_bps_max": 20,
      "sample_count": 1320,
      "wins": 1315,
      "p_win": 0.996212,
      "p_win_lower": 0.992239
    },
    {
      "remaining_sec": 60,
      "vol_bin": "low",
      "side_leading": "up_leading",
      "abs_d_bps_min": 20,
      "abs_d_bps_max": 25,
      "sample_count": 538,
      "wins": 537,
      "p_win": 0.998141,
      "p_win_lower": 0.991712
    },
    {
      "remaining_sec": 60,
      "vol_bin": "low",
      "side_leading": "down_leading",
      "abs_d_bps_min": 0,
      "abs_d_bps_max": 2,
      "sample_count": 1636,
      "wins": 996,
      "p_win": 0.608802,
      "p_win_lower": 0.588791
    },
    {
      "remaining_sec": 60,
      "vol_bin": "low",
      "side_leading": "down_leading",
      "abs_d_bps_min": 2,
      "abs_d_bps_max": 4,
      "sample_count": 3014,
      "wins": 2267,
      "p_win": 0.752157,
      "p_win_lower": 0.738998
    },
    {
      "remaining_sec": 60,
      "vol_bin": "low",
      "side_leading": "down_leading",
      "abs_d_bps_min": 4,
      "abs_d_bps_max": 6,
      "sample_count": 2728,
      "wins": 2396,
      "p_win": 0.878299,
      "p_win_lower": 0.867626
    },
    {
      "remaining_sec": 60,
      "vol_bin": "low",
      "side_leading": "down_leading",
      "abs_d_bps_min": 6,
      "abs_d_bps_max": 8,
      "sample_count": 2185,
      "wins": 2044,
      "p_win": 0.935469,
      "p_win_lower": 0.926273
    },
    {
      "remaining_sec": 60,
      "vol_bin": "low",
      "side_leading": "down_leading",
      "abs_d_bps_min": 8,
      "abs_d_bps_max": 10,
      "sample_count": 1752,
      "wins": 1691,
      "p_win": 0.965183,
      "p_win_lower": 0.957231
    },
    {
      "remaining_sec": 60,
      "vol_bin": "low",
      "side_leading": "down_leading",
      "abs_d_bps_min": 10,
      "abs_d_bps_max": 15,
      "sample_count": 2907,
      "wins": 2861,
      "p_win": 0.984176,
      "p_win_lower": 0.979894
    },
    {
      "remaining_sec": 60,
      "vol_bin": "low",
      "side_leading": "down_leading",
      "abs_d_bps_min": 15,
      "abs_d_bps_max": 20,
      "sample_count": 1479,
      "wins": 1469,
      "p_win": 0.993239,
      "p_win_lower": 0.988722
    },
    {
      "remaining_sec": 60,
      "vol_bin": "low",
      "side_leading": "down_leading",
      "abs_d_bps_min": 20,
      "abs_d_bps_max": 25,
      "sample_count": 657,
      "wins": 656,
      "p_win": 0.998478,
      "p_win_lower": 0.993207
    },
    {
      "remaining_sec": 60,
      "vol_bin": "normal",
      "side_leading": "up_leading",
      "abs_d_bps_min": 0,
      "abs_d_bps_max": 2,
      "sample_count": 1003,
      "wins": 568,
      "p_win": 0.566301,
      "p_win_lower": 0.540417
    },
    {
      "remaining_sec": 60,
      "vol_bin": "normal",
      "side_leading": "up_leading",
      "abs_d_bps_min": 2,
      "abs_d_bps_max": 4,
      "sample_count": 2006,
      "wins": 1360,
      "p_win": 0.677966,
      "p_win_lower": 0.660576
    },
    {
      "remaining_sec": 60,
      "vol_bin": "normal",
      "side_leading": "up_leading",
      "abs_d_bps_min": 4,
      "abs_d_bps_max": 6,
      "sample_count": 1854,
      "wins": 1442,
      "p_win": 0.777778,
      "p_win_lower": 0.761497
    },
    {
      "remaining_sec": 60,
      "vol_bin": "normal",
      "side_leading": "up_leading",
      "abs_d_bps_min": 6,
      "abs_d_bps_max": 8,
      "sample_count": 1674,
      "wins": 1445,
      "p_win": 0.863202,
      "p_win_lower": 0.848799
    },
    {
      "remaining_sec": 60,
      "vol_bin": "normal",
      "side_leading": "up_leading",
      "abs_d_bps_min": 8,
      "abs_d_bps_max": 10,
      "sample_count": 1570,
      "wins": 1452,
      "p_win": 0.924841,
      "p_win_lower": 0.91315
    },
    {
      "remaining_sec": 60,
      "vol_bin": "normal",
      "side_leading": "up_leading",
      "abs_d_bps_min": 10,
      "abs_d_bps_max": 15,
      "sample_count": 3184,
      "wins": 3054,
      "p_win": 0.959171,
      "p_win_lower": 0.953001
    },
    {
      "remaining_sec": 60,
      "vol_bin": "normal",
      "side_leading": "up_leading",
      "abs_d_bps_min": 15,
      "abs_d_bps_max": 20,
      "sample_count": 2269,
      "wins": 2244,
      "p_win": 0.988982,
      "p_win_lower": 0.98475
    },
    {
      "remaining_sec": 60,
      "vol_bin": "normal",
      "side_leading": "up_leading",
      "abs_d_bps_min": 20,
      "abs_d_bps_max": 25,
      "sample_count": 1455,
      "wins": 1450,
      "p_win": 0.996564,
      "p_win_lower": 0.992957
    },
    {
      "remaining_sec": 60,
      "vol_bin": "normal",
      "side_leading": "up_leading",
      "abs_d_bps_min": 25,
      "abs_d_bps_max": 30,
      "sample_count": 994,
      "wins": 992,
      "p_win": 0.997988,
      "p_win_lower": 0.993938
    },
    {
      "remaining_sec": 60,
      "vol_bin": "normal",
      "side_leading": "up_leading",
      "abs_d_bps_min": 30,
      "abs_d_bps_max": 40,
      "sample_count": 846,
      "wins": 846,
      "p_win": 1,
      "p_win_lower": 0.996812
    },
    {
      "remaining_sec": 60,
      "vol_bin": "normal",
      "side_leading": "down_leading",
      "abs_d_bps_min": 0,
      "abs_d_bps_max": 2,
      "sample_count": 950,
      "wins": 529,
      "p_win": 0.556842,
      "p_win_lower": 0.530207
    },
    {
      "remaining_sec": 60,
      "vol_bin": "normal",
      "side_leading": "down_leading",
      "abs_d_bps_min": 2,
      "abs_d_bps_max": 4,
      "sample_count": 1917,
      "wins": 1286,
      "p_win": 0.67084,
      "p_win_lower": 0.652956
    },
    {
      "remaining_sec": 60,
      "vol_bin": "normal",
      "side_leading": "down_leading",
      "abs_d_bps_min": 4,
      "abs_d_bps_max": 6,
      "sample_count": 1883,
      "wins": 1490,
      "p_win": 0.79129,
      "p_win_lower": 0.775473
    },
    {
      "remaining_sec": 60,
      "vol_bin": "normal",
      "side_leading": "down_leading",
      "abs_d_bps_min": 6,
      "abs_d_bps_max": 8,
      "sample_count": 1673,
      "wins": 1418,
      "p_win": 0.847579,
      "p_win_lower": 0.832564
    },
    {
      "remaining_sec": 60,
      "vol_bin": "normal",
      "side_leading": "down_leading",
      "abs_d_bps_min": 8,
      "abs_d_bps_max": 10,
      "sample_count": 1632,
      "wins": 1495,
      "p_win": 0.916054,
      "p_win_lower": 0.904062
    },
    {
      "remaining_sec": 60,
      "vol_bin": "normal",
      "side_leading": "down_leading",
      "abs_d_bps_min": 10,
      "abs_d_bps_max": 15,
      "sample_count": 3299,
      "wins": 3181,
      "p_win": 0.964232,
      "p_win_lower": 0.958521
    },
    {
      "remaining_sec": 60,
      "vol_bin": "normal",
      "side_leading": "down_leading",
      "abs_d_bps_min": 15,
      "abs_d_bps_max": 20,
      "sample_count": 2301,
      "wins": 2277,
      "p_win": 0.98957,
      "p_win_lower": 0.985466
    },
    {
      "remaining_sec": 60,
      "vol_bin": "normal",
      "side_leading": "down_leading",
      "abs_d_bps_min": 20,
      "abs_d_bps_max": 25,
      "sample_count": 1486,
      "wins": 1477,
      "p_win": 0.993943,
      "p_win_lower": 0.989618
    },
    {
      "remaining_sec": 60,
      "vol_bin": "normal",
      "side_leading": "down_leading",
      "abs_d_bps_min": 25,
      "abs_d_bps_max": 30,
      "sample_count": 921,
      "wins": 920,
      "p_win": 0.998914,
      "p_win_lower": 0.995148
    },
    {
      "remaining_sec": 60,
      "vol_bin": "normal",
      "side_leading": "down_leading",
      "abs_d_bps_min": 30,
      "abs_d_bps_max": 40,
      "sample_count": 889,
      "wins": 888,
      "p_win": 0.998875,
      "p_win_lower": 0.994974
    },
    {
      "remaining_sec": 60,
      "vol_bin": "high",
      "side_leading": "up_leading",
      "abs_d_bps_min": 2,
      "abs_d_bps_max": 4,
      "sample_count": 850,
      "wins": 522,
      "p_win": 0.614118,
      "p_win_lower": 0.586332
    },
    {
      "remaining_sec": 60,
      "vol_bin": "high",
      "side_leading": "up_leading",
      "abs_d_bps_min": 4,
      "abs_d_bps_max": 6,
      "sample_count": 891,
      "wins": 625,
      "p_win": 0.701459,
      "p_win_lower": 0.675662
    },
    {
      "remaining_sec": 60,
      "vol_bin": "high",
      "side_leading": "up_leading",
      "abs_d_bps_min": 6,
      "abs_d_bps_max": 8,
      "sample_count": 820,
      "wins": 627,
      "p_win": 0.764634,
      "p_win_lower": 0.73942
    },
    {
      "remaining_sec": 60,
      "vol_bin": "high",
      "side_leading": "up_leading",
      "abs_d_bps_min": 8,
      "abs_d_bps_max": 10,
      "sample_count": 813,
      "wins": 683,
      "p_win": 0.840098,
      "p_win_lower": 0.817831
    },
    {
      "remaining_sec": 60,
      "vol_bin": "high",
      "side_leading": "up_leading",
      "abs_d_bps_min": 10,
      "abs_d_bps_max": 15,
      "sample_count": 1793,
      "wins": 1643,
      "p_win": 0.916341,
      "p_win_lower": 0.904948
    },
    {
      "remaining_sec": 60,
      "vol_bin": "high",
      "side_leading": "up_leading",
      "abs_d_bps_min": 15,
      "abs_d_bps_max": 20,
      "sample_count": 1585,
      "wins": 1534,
      "p_win": 0.967823,
      "p_win_lower": 0.959698
    },
    {
      "remaining_sec": 60,
      "vol_bin": "high",
      "side_leading": "up_leading",
      "abs_d_bps_min": 20,
      "abs_d_bps_max": 25,
      "sample_count": 1180,
      "wins": 1157,
      "p_win": 0.980508,
      "p_win_lower": 0.972706
    },
    {
      "remaining_sec": 60,
      "vol_bin": "high",
      "side_leading": "up_leading",
      "abs_d_bps_min": 25,
      "abs_d_bps_max": 30,
      "sample_count": 918,
      "wins": 912,
      "p_win": 0.993464,
      "p_win_lower": 0.987411
    },
    {
      "remaining_sec": 60,
      "vol_bin": "high",
      "side_leading": "up_leading",
      "abs_d_bps_min": 30,
      "abs_d_bps_max": 40,
      "sample_count": 1148,
      "wins": 1145,
      "p_win": 0.997387,
      "p_win_lower": 0.993479
    },
    {
      "remaining_sec": 60,
      "vol_bin": "high",
      "side_leading": "up_leading",
      "abs_d_bps_min": 40,
      "abs_d_bps_max": 50,
      "sample_count": 693,
      "wins": 693,
      "p_win": 1,
      "p_win_lower": 0.996111
    },
    {
      "remaining_sec": 60,
      "vol_bin": "high",
      "side_leading": "up_leading",
      "abs_d_bps_min": 50,
      "abs_d_bps_max": 75,
      "sample_count": 513,
      "wins": 513,
      "p_win": 1,
      "p_win_lower": 0.994753
    },
    {
      "remaining_sec": 60,
      "vol_bin": "high",
      "side_leading": "down_leading",
      "abs_d_bps_min": 2,
      "abs_d_bps_max": 4,
      "sample_count": 972,
      "wins": 629,
      "p_win": 0.647119,
      "p_win_lower": 0.62153
    },
    {
      "remaining_sec": 60,
      "vol_bin": "high",
      "side_leading": "down_leading",
      "abs_d_bps_min": 4,
      "abs_d_bps_max": 6,
      "sample_count": 910,
      "wins": 654,
      "p_win": 0.718681,
      "p_win_lower": 0.693543
    },
    {
      "remaining_sec": 60,
      "vol_bin": "high",
      "side_leading": "down_leading",
      "abs_d_bps_min": 6,
      "abs_d_bps_max": 8,
      "sample_count": 898,
      "wins": 716,
      "p_win": 0.797327,
      "p_win_lower": 0.774384
    },
    {
      "remaining_sec": 60,
      "vol_bin": "high",
      "side_leading": "down_leading",
      "abs_d_bps_min": 8,
      "abs_d_bps_max": 10,
      "sample_count": 823,
      "wins": 680,
      "p_win": 0.826245,
      "p_win_lower": 0.803461
    },
    {
      "remaining_sec": 60,
      "vol_bin": "high",
      "side_leading": "down_leading",
      "abs_d_bps_min": 10,
      "abs_d_bps_max": 15,
      "sample_count": 1827,
      "wins": 1654,
      "p_win": 0.905309,
      "p_win_lower": 0.893435
    },
    {
      "remaining_sec": 60,
      "vol_bin": "high",
      "side_leading": "down_leading",
      "abs_d_bps_min": 15,
      "abs_d_bps_max": 20,
      "sample_count": 1460,
      "wins": 1408,
      "p_win": 0.964384,
      "p_win_lower": 0.955507
    },
    {
      "remaining_sec": 60,
      "vol_bin": "high",
      "side_leading": "down_leading",
      "abs_d_bps_min": 20,
      "abs_d_bps_max": 25,
      "sample_count": 1129,
      "wins": 1110,
      "p_win": 0.983171,
      "p_win_lower": 0.975621
    },
    {
      "remaining_sec": 60,
      "vol_bin": "high",
      "side_leading": "down_leading",
      "abs_d_bps_min": 25,
      "abs_d_bps_max": 30,
      "sample_count": 881,
      "wins": 872,
      "p_win": 0.989784,
      "p_win_lower": 0.982522
    },
    {
      "remaining_sec": 60,
      "vol_bin": "high",
      "side_leading": "down_leading",
      "abs_d_bps_min": 30,
      "abs_d_bps_max": 40,
      "sample_count": 1237,
      "wins": 1232,
      "p_win": 0.995958,
      "p_win_lower": 0.99172
    },
    {
      "remaining_sec": 60,
      "vol_bin": "high",
      "side_leading": "down_leading",
      "abs_d_bps_min": 40,
      "abs_d_bps_max": 50,
      "sample_count": 684,
      "wins": 684,
      "p_win": 1,
      "p_win_lower": 0.99606
    },
    {
      "remaining_sec": 60,
      "vol_bin": "high",
      "side_leading": "down_leading",
      "abs_d_bps_min": 50,
      "abs_d_bps_max": 75,
      "sample_count": 539,
      "wins": 539,
      "p_win": 1,
      "p_win_lower": 0.995005
    },
    {
      "remaining_sec": 60,
      "vol_bin": "extreme",
      "side_leading": "up_leading",
      "abs_d_bps_min": 10,
      "abs_d_bps_max": 15,
      "sample_count": 584,
      "wins": 482,
      "p_win": 0.825342,
      "p_win_lower": 0.798015
    },
    {
      "remaining_sec": 60,
      "vol_bin": "extreme",
      "side_leading": "up_leading",
      "abs_d_bps_min": 15,
      "abs_d_bps_max": 20,
      "sample_count": 500,
      "wins": 449,
      "p_win": 0.898,
      "p_win_lower": 0.873551
    },
    {
      "remaining_sec": 60,
      "vol_bin": "extreme",
      "side_leading": "up_leading",
      "abs_d_bps_min": 30,
      "abs_d_bps_max": 40,
      "sample_count": 663,
      "wins": 655,
      "p_win": 0.987934,
      "p_win_lower": 0.978713
    },
    {
      "remaining_sec": 60,
      "vol_bin": "extreme",
      "side_leading": "up_leading",
      "abs_d_bps_min": 50,
      "abs_d_bps_max": 75,
      "sample_count": 620,
      "wins": 614,
      "p_win": 0.990323,
      "p_win_lower": 0.981396
    },
    {
      "remaining_sec": 60,
      "vol_bin": "extreme",
      "side_leading": "down_leading",
      "abs_d_bps_min": 10,
      "abs_d_bps_max": 15,
      "sample_count": 551,
      "wins": 457,
      "p_win": 0.829401,
      "p_win_lower": 0.801447
    },
    {
      "remaining_sec": 60,
      "vol_bin": "extreme",
      "side_leading": "down_leading",
      "abs_d_bps_min": 15,
      "abs_d_bps_max": 20,
      "sample_count": 548,
      "wins": 497,
      "p_win": 0.906934,
      "p_win_lower": 0.884473
    },
    {
      "remaining_sec": 60,
      "vol_bin": "extreme",
      "side_leading": "down_leading",
      "abs_d_bps_min": 30,
      "abs_d_bps_max": 40,
      "sample_count": 648,
      "wins": 641,
      "p_win": 0.989198,
      "p_win_lower": 0.980194
    },
    {
      "remaining_sec": 60,
      "vol_bin": "extreme",
      "side_leading": "down_leading",
      "abs_d_bps_min": 50,
      "abs_d_bps_max": 75,
      "sample_count": 567,
      "wins": 561,
      "p_win": 0.989418,
      "p_win_lower": 0.979669
    },
    {
      "remaining_sec": 120,
      "vol_bin": "low",
      "side_leading": "up_leading",
      "abs_d_bps_min": 0,
      "abs_d_bps_max": 2,
      "sample_count": 1902,
      "wins": 1056,
      "p_win": 0.555205,
      "p_win_lower": 0.536397
    },
    {
      "remaining_sec": 120,
      "vol_bin": "low",
      "side_leading": "up_leading",
      "abs_d_bps_min": 2,
      "abs_d_bps_max": 4,
      "sample_count": 3562,
      "wins": 2363,
      "p_win": 0.663391,
      "p_win_lower": 0.650248
    },
    {
      "remaining_sec": 120,
      "vol_bin": "low",
      "side_leading": "up_leading",
      "abs_d_bps_min": 4,
      "abs_d_bps_max": 6,
      "sample_count": 2952,
      "wins": 2279,
      "p_win": 0.772019,
      "p_win_lower": 0.759072
    },
    {
      "remaining_sec": 120,
      "vol_bin": "low",
      "side_leading": "up_leading",
      "abs_d_bps_min": 6,
      "abs_d_bps_max": 8,
      "sample_count": 2226,
      "wins": 1851,
      "p_win": 0.831536,
      "p_win_lower": 0.818087
    },
    {
      "remaining_sec": 120,
      "vol_bin": "low",
      "side_leading": "up_leading",
      "abs_d_bps_min": 8,
      "abs_d_bps_max": 10,
      "sample_count": 1703,
      "wins": 1526,
      "p_win": 0.896066,
      "p_win_lower": 0.883267
    },
    {
      "remaining_sec": 120,
      "vol_bin": "low",
      "side_leading": "up_leading",
      "abs_d_bps_min": 10,
      "abs_d_bps_max": 15,
      "sample_count": 2425,
      "wins": 2273,
      "p_win": 0.93732,
      "p_win_lower": 0.928726
    },
    {
      "remaining_sec": 120,
      "vol_bin": "low",
      "side_leading": "up_leading",
      "abs_d_bps_min": 15,
      "abs_d_bps_max": 20,
      "sample_count": 947,
      "wins": 909,
      "p_win": 0.959873,
      "p_win_lower": 0.948006
    },
    {
      "remaining_sec": 120,
      "vol_bin": "low",
      "side_leading": "down_leading",
      "abs_d_bps_min": 0,
      "abs_d_bps_max": 2,
      "sample_count": 1828,
      "wins": 1058,
      "p_win": 0.578775,
      "p_win_lower": 0.559676
    },
    {
      "remaining_sec": 120,
      "vol_bin": "low",
      "side_leading": "down_leading",
      "abs_d_bps_min": 2,
      "abs_d_bps_max": 4,
      "sample_count": 3456,
      "wins": 2350,
      "p_win": 0.679977,
      "p_win_lower": 0.666788
    },
    {
      "remaining_sec": 120,
      "vol_bin": "low",
      "side_leading": "down_leading",
      "abs_d_bps_min": 4,
      "abs_d_bps_max": 6,
      "sample_count": 2940,
      "wins": 2259,
      "p_win": 0.768367,
      "p_win_lower": 0.755326
    },
    {
      "remaining_sec": 120,
      "vol_bin": "low",
      "side_leading": "down_leading",
      "abs_d_bps_min": 6,
      "abs_d_bps_max": 8,
      "sample_count": 2319,
      "wins": 1964,
      "p_win": 0.846917,
      "p_win_lower": 0.834214
    },
    {
      "remaining_sec": 120,
      "vol_bin": "low",
      "side_leading": "down_leading",
      "abs_d_bps_min": 8,
      "abs_d_bps_max": 10,
      "sample_count": 1702,
      "wins": 1516,
      "p_win": 0.890717,
      "p_win_lower": 0.877651
    },
    {
      "remaining_sec": 120,
      "vol_bin": "low",
      "side_leading": "down_leading",
      "abs_d_bps_min": 10,
      "abs_d_bps_max": 15,
      "sample_count": 2540,
      "wins": 2400,
      "p_win": 0.944882,
      "p_win_lower": 0.936949
    },
    {
      "remaining_sec": 120,
      "vol_bin": "low",
      "side_leading": "down_leading",
      "abs_d_bps_min": 15,
      "abs_d_bps_max": 20,
      "sample_count": 1027,
      "wins": 991,
      "p_win": 0.964946,
      "p_win_lower": 0.954218
    },
    {
      "remaining_sec": 120,
      "vol_bin": "normal",
      "side_leading": "up_leading",
      "abs_d_bps_min": 0,
      "abs_d_bps_max": 2,
      "sample_count": 1251,
      "wins": 695,
      "p_win": 0.555556,
      "p_win_lower": 0.532351
    },
    {
      "remaining_sec": 120,
      "vol_bin": "normal",
      "side_leading": "up_leading",
      "abs_d_bps_min": 2,
      "abs_d_bps_max": 4,
      "sample_count": 2276,
      "wins": 1406,
      "p_win": 0.61775,
      "p_win_lower": 0.600865
    },
    {
      "remaining_sec": 120,
      "vol_bin": "normal",
      "side_leading": "up_leading",
      "abs_d_bps_min": 4,
      "abs_d_bps_max": 6,
      "sample_count": 2179,
      "wins": 1509,
      "p_win": 0.69252,
      "p_win_lower": 0.676029
    },
    {
      "remaining_sec": 120,
      "vol_bin": "normal",
      "side_leading": "up_leading",
      "abs_d_bps_min": 6,
      "abs_d_bps_max": 8,
      "sample_count": 2019,
      "wins": 1520,
      "p_win": 0.752848,
      "p_win_lower": 0.736726
    },
    {
      "remaining_sec": 120,
      "vol_bin": "normal",
      "side_leading": "up_leading",
      "abs_d_bps_min": 8,
      "abs_d_bps_max": 10,
      "sample_count": 1766,
      "wins": 1436,
      "p_win": 0.813137,
      "p_win_lower": 0.797405
    },
    {
      "remaining_sec": 120,
      "vol_bin": "normal",
      "side_leading": "up_leading",
      "abs_d_bps_min": 10,
      "abs_d_bps_max": 15,
      "sample_count": 3261,
      "wins": 2843,
      "p_win": 0.871818,
      "p_win_lower": 0.86188
    },
    {
      "remaining_sec": 120,
      "vol_bin": "normal",
      "side_leading": "up_leading",
      "abs_d_bps_min": 15,
      "abs_d_bps_max": 20,
      "sample_count": 1975,
      "wins": 1850,
      "p_win": 0.936709,
      "p_win_lower": 0.927086
    },
    {
      "remaining_sec": 120,
      "vol_bin": "normal",
      "side_leading": "up_leading",
      "abs_d_bps_min": 20,
      "abs_d_bps_max": 25,
      "sample_count": 1183,
      "wins": 1150,
      "p_win": 0.972105,
      "p_win_lower": 0.963088
    },
    {
      "remaining_sec": 120,
      "vol_bin": "normal",
      "side_leading": "up_leading",
      "abs_d_bps_min": 25,
      "abs_d_bps_max": 30,
      "sample_count": 651,
      "wins": 647,
      "p_win": 0.993856,
      "p_win_lower": 0.986384
    },
    {
      "remaining_sec": 120,
      "vol_bin": "normal",
      "side_leading": "up_leading",
      "abs_d_bps_min": 30,
      "abs_d_bps_max": 40,
      "sample_count": 519,
      "wins": 512,
      "p_win": 0.986513,
      "p_win_lower": 0.975308
    },
    {
      "remaining_sec": 120,
      "vol_bin": "normal",
      "side_leading": "down_leading",
      "abs_d_bps_min": 0,
      "abs_d_bps_max": 2,
      "sample_count": 1226,
      "wins": 657,
      "p_win": 0.535889,
      "p_win_lower": 0.512407
    },
    {
      "remaining_sec": 120,
      "vol_bin": "normal",
      "side_leading": "down_leading",
      "abs_d_bps_min": 2,
      "abs_d_bps_max": 4,
      "sample_count": 2325,
      "wins": 1440,
      "p_win": 0.619355,
      "p_win_lower": 0.602661
    },
    {
      "remaining_sec": 120,
      "vol_bin": "normal",
      "side_leading": "down_leading",
      "abs_d_bps_min": 4,
      "abs_d_bps_max": 6,
      "sample_count": 2144,
      "wins": 1501,
      "p_win": 0.700093,
      "p_win_lower": 0.683572
    },
    {
      "remaining_sec": 120,
      "vol_bin": "normal",
      "side_leading": "down_leading",
      "abs_d_bps_min": 6,
      "abs_d_bps_max": 8,
      "sample_count": 1970,
      "wins": 1482,
      "p_win": 0.752284,
      "p_win_lower": 0.735947
    },
    {
      "remaining_sec": 120,
      "vol_bin": "normal",
      "side_leading": "down_leading",
      "abs_d_bps_min": 8,
      "abs_d_bps_max": 10,
      "sample_count": 1716,
      "wins": 1427,
      "p_win": 0.831585,
      "p_win_lower": 0.816205
    },
    {
      "remaining_sec": 120,
      "vol_bin": "normal",
      "side_leading": "down_leading",
      "abs_d_bps_min": 10,
      "abs_d_bps_max": 15,
      "sample_count": 3329,
      "wins": 2949,
      "p_win": 0.885852,
      "p_win_lower": 0.876471
    },
    {
      "remaining_sec": 120,
      "vol_bin": "normal",
      "side_leading": "down_leading",
      "abs_d_bps_min": 15,
      "abs_d_bps_max": 20,
      "sample_count": 2019,
      "wins": 1906,
      "p_win": 0.944032,
      "p_win_lower": 0.935007
    },
    {
      "remaining_sec": 120,
      "vol_bin": "normal",
      "side_leading": "down_leading",
      "abs_d_bps_min": 20,
      "abs_d_bps_max": 25,
      "sample_count": 1123,
      "wins": 1085,
      "p_win": 0.966162,
      "p_win_lower": 0.956107
    },
    {
      "remaining_sec": 120,
      "vol_bin": "normal",
      "side_leading": "down_leading",
      "abs_d_bps_min": 25,
      "abs_d_bps_max": 30,
      "sample_count": 627,
      "wins": 614,
      "p_win": 0.979266,
      "p_win_lower": 0.967642
    },
    {
      "remaining_sec": 120,
      "vol_bin": "normal",
      "side_leading": "down_leading",
      "abs_d_bps_min": 30,
      "abs_d_bps_max": 40,
      "sample_count": 554,
      "wins": 549,
      "p_win": 0.990975,
      "p_win_lower": 0.981577
    },
    {
      "remaining_sec": 120,
      "vol_bin": "high",
      "side_leading": "up_leading",
      "abs_d_bps_min": 0,
      "abs_d_bps_max": 2,
      "sample_count": 573,
      "wins": 291,
      "p_win": 0.507853,
      "p_win_lower": 0.473543
    },
    {
      "remaining_sec": 120,
      "vol_bin": "high",
      "side_leading": "up_leading",
      "abs_d_bps_min": 2,
      "abs_d_bps_max": 4,
      "sample_count": 1141,
      "wins": 656,
      "p_win": 0.574934,
      "p_win_lower": 0.550712
    },
    {
      "remaining_sec": 120,
      "vol_bin": "high",
      "side_leading": "up_leading",
      "abs_d_bps_min": 4,
      "abs_d_bps_max": 6,
      "sample_count": 1047,
      "wins": 657,
      "p_win": 0.627507,
      "p_win_lower": 0.602631
    },
    {
      "remaining_sec": 120,
      "vol_bin": "high",
      "side_leading": "up_leading",
      "abs_d_bps_min": 6,
      "abs_d_bps_max": 8,
      "sample_count": 952,
      "wins": 638,
      "p_win": 0.670168,
      "p_win_lower": 0.644652
    },
    {
      "remaining_sec": 120,
      "vol_bin": "high",
      "side_leading": "up_leading",
      "abs_d_bps_min": 8,
      "abs_d_bps_max": 10,
      "sample_count": 972,
      "wins": 703,
      "p_win": 0.723251,
      "p_win_lower": 0.699051
    },
    {
      "remaining_sec": 120,
      "vol_bin": "high",
      "side_leading": "up_leading",
      "abs_d_bps_min": 10,
      "abs_d_bps_max": 15,
      "sample_count": 1964,
      "wins": 1549,
      "p_win": 0.788697,
      "p_win_lower": 0.773152
    },
    {
      "remaining_sec": 120,
      "vol_bin": "high",
      "side_leading": "up_leading",
      "abs_d_bps_min": 15,
      "abs_d_bps_max": 20,
      "sample_count": 1502,
      "wins": 1345,
      "p_win": 0.895473,
      "p_win_lower": 0.881769
    },
    {
      "remaining_sec": 120,
      "vol_bin": "high",
      "side_leading": "up_leading",
      "abs_d_bps_min": 20,
      "abs_d_bps_max": 25,
      "sample_count": 1139,
      "wins": 1058,
      "p_win": 0.928885,
      "p_win_lower": 0.915315
    },
    {
      "remaining_sec": 120,
      "vol_bin": "high",
      "side_leading": "up_leading",
      "abs_d_bps_min": 25,
      "abs_d_bps_max": 30,
      "sample_count": 804,
      "wins": 767,
      "p_win": 0.95398,
      "p_win_lower": 0.940228
    },
    {
      "remaining_sec": 120,
      "vol_bin": "high",
      "side_leading": "up_leading",
      "abs_d_bps_min": 30,
      "abs_d_bps_max": 40,
      "sample_count": 901,
      "wins": 883,
      "p_win": 0.980022,
      "p_win_lower": 0.970795
    },
    {
      "remaining_sec": 120,
      "vol_bin": "high",
      "side_leading": "down_leading",
      "abs_d_bps_min": 0,
      "abs_d_bps_max": 2,
      "sample_count": 573,
      "wins": 294,
      "p_win": 0.513089,
      "p_win_lower": 0.478762
    },
    {
      "remaining_sec": 120,
      "vol_bin": "high",
      "side_leading": "down_leading",
      "abs_d_bps_min": 2,
      "abs_d_bps_max": 4,
      "sample_count": 1120,
      "wins": 654,
      "p_win": 0.583929,
      "p_win_lower": 0.559528
    },
    {
      "remaining_sec": 120,
      "vol_bin": "high",
      "side_leading": "down_leading",
      "abs_d_bps_min": 4,
      "abs_d_bps_max": 6,
      "sample_count": 1096,
      "wins": 733,
      "p_win": 0.668796,
      "p_win_lower": 0.645021
    },
    {
      "remaining_sec": 120,
      "vol_bin": "high",
      "side_leading": "down_leading",
      "abs_d_bps_min": 6,
      "abs_d_bps_max": 8,
      "sample_count": 1077,
      "wins": 736,
      "p_win": 0.68338,
      "p_win_lower": 0.65963
    },
    {
      "remaining_sec": 120,
      "vol_bin": "high",
      "side_leading": "down_leading",
      "abs_d_bps_min": 8,
      "abs_d_bps_max": 10,
      "sample_count": 924,
      "wins": 689,
      "p_win": 0.745671,
      "p_win_lower": 0.721412
    },
    {
      "remaining_sec": 120,
      "vol_bin": "high",
      "side_leading": "down_leading",
      "abs_d_bps_min": 10,
      "abs_d_bps_max": 15,
      "sample_count": 1985,
      "wins": 1606,
      "p_win": 0.809068,
      "p_win_lower": 0.79414
    },
    {
      "remaining_sec": 120,
      "vol_bin": "high",
      "side_leading": "down_leading",
      "abs_d_bps_min": 15,
      "abs_d_bps_max": 20,
      "sample_count": 1524,
      "wins": 1326,
      "p_win": 0.870079,
      "p_win_lower": 0.855254
    },
    {
      "remaining_sec": 120,
      "vol_bin": "high",
      "side_leading": "down_leading",
      "abs_d_bps_min": 20,
      "abs_d_bps_max": 25,
      "sample_count": 1069,
      "wins": 994,
      "p_win": 0.929841,
      "p_win_lower": 0.915876
    },
    {
      "remaining_sec": 120,
      "vol_bin": "high",
      "side_leading": "down_leading",
      "abs_d_bps_min": 25,
      "abs_d_bps_max": 30,
      "sample_count": 807,
      "wins": 768,
      "p_win": 0.951673,
      "p_win_lower": 0.937675
    },
    {
      "remaining_sec": 120,
      "vol_bin": "high",
      "side_leading": "down_leading",
      "abs_d_bps_min": 30,
      "abs_d_bps_max": 40,
      "sample_count": 908,
      "wins": 880,
      "p_win": 0.969163,
      "p_win_lower": 0.958244
    },
    {
      "remaining_sec": 120,
      "vol_bin": "extreme",
      "side_leading": "up_leading",
      "abs_d_bps_min": 10,
      "abs_d_bps_max": 15,
      "sample_count": 686,
      "wins": 516,
      "p_win": 0.752187,
      "p_win_lower": 0.724116
    },
    {
      "remaining_sec": 120,
      "vol_bin": "extreme",
      "side_leading": "up_leading",
      "abs_d_bps_min": 15,
      "abs_d_bps_max": 20,
      "sample_count": 590,
      "wins": 473,
      "p_win": 0.801695,
      "p_win_lower": 0.773343
    },
    {
      "remaining_sec": 120,
      "vol_bin": "extreme",
      "side_leading": "up_leading",
      "abs_d_bps_min": 20,
      "abs_d_bps_max": 25,
      "sample_count": 503,
      "wins": 419,
      "p_win": 0.833002,
      "p_win_lower": 0.803881
    },
    {
      "remaining_sec": 120,
      "vol_bin": "extreme",
      "side_leading": "up_leading",
      "abs_d_bps_min": 30,
      "abs_d_bps_max": 40,
      "sample_count": 606,
      "wins": 569,
      "p_win": 0.938944,
      "p_win_lower": 0.920911
    },
    {
      "remaining_sec": 120,
      "vol_bin": "extreme",
      "side_leading": "down_leading",
      "abs_d_bps_min": 10,
      "abs_d_bps_max": 15,
      "sample_count": 696,
      "wins": 507,
      "p_win": 0.728448,
      "p_win_lower": 0.699873
    },
    {
      "remaining_sec": 120,
      "vol_bin": "extreme",
      "side_leading": "down_leading",
      "abs_d_bps_min": 15,
      "abs_d_bps_max": 20,
      "sample_count": 554,
      "wins": 436,
      "p_win": 0.787004,
      "p_win_lower": 0.757032
    },
    {
      "remaining_sec": 120,
      "vol_bin": "extreme",
      "side_leading": "down_leading",
      "abs_d_bps_min": 30,
      "abs_d_bps_max": 40,
      "sample_count": 587,
      "wins": 536,
      "p_win": 0.913118,
      "p_win_lower": 0.892049
    },
    {
      "remaining_sec": 180,
      "vol_bin": "low",
      "side_leading": "up_leading",
      "abs_d_bps_min": 0,
      "abs_d_bps_max": 2,
      "sample_count": 2357,
      "wins": 1311,
      "p_win": 0.556216,
      "p_win_lower": 0.539327
    },
    {
      "remaining_sec": 180,
      "vol_bin": "low",
      "side_leading": "up_leading",
      "abs_d_bps_min": 2,
      "abs_d_bps_max": 4,
      "sample_count": 4407,
      "wins": 2716,
      "p_win": 0.616292,
      "p_win_lower": 0.604175
    },
    {
      "remaining_sec": 180,
      "vol_bin": "low",
      "side_leading": "up_leading",
      "abs_d_bps_min": 4,
      "abs_d_bps_max": 6,
      "sample_count": 3294,
      "wins": 2345,
      "p_win": 0.7119,
      "p_win_lower": 0.698751
    },
    {
      "remaining_sec": 180,
      "vol_bin": "low",
      "side_leading": "up_leading",
      "abs_d_bps_min": 6,
      "abs_d_bps_max": 8,
      "sample_count": 2211,
      "wins": 1731,
      "p_win": 0.782904,
      "p_win_lower": 0.768141
    },
    {
      "remaining_sec": 180,
      "vol_bin": "low",
      "side_leading": "up_leading",
      "abs_d_bps_min": 8,
      "abs_d_bps_max": 10,
      "sample_count": 1467,
      "wins": 1216,
      "p_win": 0.828903,
      "p_win_lower": 0.812127
    },
    {
      "remaining_sec": 180,
      "vol_bin": "low",
      "side_leading": "up_leading",
      "abs_d_bps_min": 10,
      "abs_d_bps_max": 15,
      "sample_count": 1745,
      "wins": 1521,
      "p_win": 0.871633,
      "p_win_lower": 0.857884
    },
    {
      "remaining_sec": 180,
      "vol_bin": "low",
      "side_leading": "up_leading",
      "abs_d_bps_min": 15,
      "abs_d_bps_max": 20,
      "sample_count": 568,
      "wins": 526,
      "p_win": 0.926056,
      "p_win_lower": 0.905906
    },
    {
      "remaining_sec": 180,
      "vol_bin": "low",
      "side_leading": "down_leading",
      "abs_d_bps_min": 0,
      "abs_d_bps_max": 2,
      "sample_count": 2395,
      "wins": 1362,
      "p_win": 0.568685,
      "p_win_lower": 0.55197
    },
    {
      "remaining_sec": 180,
      "vol_bin": "low",
      "side_leading": "down_leading",
      "abs_d_bps_min": 2,
      "abs_d_bps_max": 4,
      "sample_count": 4120,
      "wins": 2655,
      "p_win": 0.644417,
      "p_win_lower": 0.632059
    },
    {
      "remaining_sec": 180,
      "vol_bin": "low",
      "side_leading": "down_leading",
      "abs_d_bps_min": 4,
      "abs_d_bps_max": 6,
      "sample_count": 3212,
      "wins": 2316,
      "p_win": 0.721046,
      "p_win_lower": 0.707848
    },
    {
      "remaining_sec": 180,
      "vol_bin": "low",
      "side_leading": "down_leading",
      "abs_d_bps_min": 6,
      "abs_d_bps_max": 8,
      "sample_count": 2161,
      "wins": 1704,
      "p_win": 0.788524,
      "p_win_lower": 0.773718
    },
    {
      "remaining_sec": 180,
      "vol_bin": "low",
      "side_leading": "down_leading",
      "abs_d_bps_min": 8,
      "abs_d_bps_max": 10,
      "sample_count": 1528,
      "wins": 1282,
      "p_win": 0.839005,
      "p_win_lower": 0.822942
    },
    {
      "remaining_sec": 180,
      "vol_bin": "low",
      "side_leading": "down_leading",
      "abs_d_bps_min": 10,
      "abs_d_bps_max": 15,
      "sample_count": 1754,
      "wins": 1553,
      "p_win": 0.885405,
      "p_win_lower": 0.872296
    },
    {
      "remaining_sec": 180,
      "vol_bin": "low",
      "side_leading": "down_leading",
      "abs_d_bps_min": 15,
      "abs_d_bps_max": 20,
      "sample_count": 541,
      "wins": 506,
      "p_win": 0.935305,
      "p_win_lower": 0.915651
    },
    {
      "remaining_sec": 180,
      "vol_bin": "normal",
      "side_leading": "up_leading",
      "abs_d_bps_min": 0,
      "abs_d_bps_max": 2,
      "sample_count": 1556,
      "wins": 872,
      "p_win": 0.560411,
      "p_win_lower": 0.539627
    },
    {
      "remaining_sec": 180,
      "vol_bin": "normal",
      "side_leading": "up_leading",
      "abs_d_bps_min": 2,
      "abs_d_bps_max": 4,
      "sample_count": 2980,
      "wins": 1778,
      "p_win": 0.596644,
      "p_win_lower": 0.581781
    },
    {
      "remaining_sec": 180,
      "vol_bin": "normal",
      "side_leading": "up_leading",
      "abs_d_bps_min": 4,
      "abs_d_bps_max": 6,
      "sample_count": 2710,
      "wins": 1788,
      "p_win": 0.659779,
      "p_win_lower": 0.644655
    },
    {
      "remaining_sec": 180,
      "vol_bin": "normal",
      "side_leading": "up_leading",
      "abs_d_bps_min": 6,
      "abs_d_bps_max": 8,
      "sample_count": 2201,
      "wins": 1522,
      "p_win": 0.691504,
      "p_win_lower": 0.675083
    },
    {
      "remaining_sec": 180,
      "vol_bin": "normal",
      "side_leading": "up_leading",
      "abs_d_bps_min": 8,
      "abs_d_bps_max": 10,
      "sample_count": 1804,
      "wins": 1367,
      "p_win": 0.757761,
      "p_win_lower": 0.74079
    },
    {
      "remaining_sec": 180,
      "vol_bin": "normal",
      "side_leading": "up_leading",
      "abs_d_bps_min": 10,
      "abs_d_bps_max": 15,
      "sample_count": 3003,
      "wins": 2429,
      "p_win": 0.808858,
      "p_win_lower": 0.796779
    },
    {
      "remaining_sec": 180,
      "vol_bin": "normal",
      "side_leading": "up_leading",
      "abs_d_bps_min": 15,
      "abs_d_bps_max": 20,
      "sample_count": 1534,
      "wins": 1372,
      "p_win": 0.894394,
      "p_win_lower": 0.880785
    },
    {
      "remaining_sec": 180,
      "vol_bin": "normal",
      "side_leading": "up_leading",
      "abs_d_bps_min": 20,
      "abs_d_bps_max": 25,
      "sample_count": 675,
      "wins": 619,
      "p_win": 0.917037,
      "p_win_lower": 0.897864
    },
    {
      "remaining_sec": 180,
      "vol_bin": "normal",
      "side_leading": "down_leading",
      "abs_d_bps_min": 0,
      "abs_d_bps_max": 2,
      "sample_count": 1595,
      "wins": 875,
      "p_win": 0.548589,
      "p_win_lower": 0.528028
    },
    {
      "remaining_sec": 180,
      "vol_bin": "normal",
      "side_leading": "down_leading",
      "abs_d_bps_min": 2,
      "abs_d_bps_max": 4,
      "sample_count": 2984,
      "wins": 1758,
      "p_win": 0.589142,
      "p_win_lower": 0.574253
    },
    {
      "remaining_sec": 180,
      "vol_bin": "normal",
      "side_leading": "down_leading",
      "abs_d_bps_min": 4,
      "abs_d_bps_max": 6,
      "sample_count": 2538,
      "wins": 1673,
      "p_win": 0.65918,
      "p_win_lower": 0.643542
    },
    {
      "remaining_sec": 180,
      "vol_bin": "normal",
      "side_leading": "down_leading",
      "abs_d_bps_min": 6,
      "abs_d_bps_max": 8,
      "sample_count": 2102,
      "wins": 1507,
      "p_win": 0.716936,
      "p_win_lower": 0.700503
    },
    {
      "remaining_sec": 180,
      "vol_bin": "normal",
      "side_leading": "down_leading",
      "abs_d_bps_min": 8,
      "abs_d_bps_max": 10,
      "sample_count": 1880,
      "wins": 1412,
      "p_win": 0.751064,
      "p_win_lower": 0.734307
    },
    {
      "remaining_sec": 180,
      "vol_bin": "normal",
      "side_leading": "down_leading",
      "abs_d_bps_min": 10,
      "abs_d_bps_max": 15,
      "sample_count": 3051,
      "wins": 2518,
      "p_win": 0.825303,
      "p_win_lower": 0.813709
    },
    {
      "remaining_sec": 180,
      "vol_bin": "normal",
      "side_leading": "down_leading",
      "abs_d_bps_min": 15,
      "abs_d_bps_max": 20,
      "sample_count": 1477,
      "wins": 1307,
      "p_win": 0.884902,
      "p_win_lower": 0.870533
    },
    {
      "remaining_sec": 180,
      "vol_bin": "normal",
      "side_leading": "down_leading",
      "abs_d_bps_min": 20,
      "abs_d_bps_max": 25,
      "sample_count": 735,
      "wins": 690,
      "p_win": 0.938776,
      "p_win_lower": 0.922558
    },
    {
      "remaining_sec": 180,
      "vol_bin": "high",
      "side_leading": "up_leading",
      "abs_d_bps_min": 0,
      "abs_d_bps_max": 2,
      "sample_count": 714,
      "wins": 370,
      "p_win": 0.518207,
      "p_win_lower": 0.487438
    },
    {
      "remaining_sec": 180,
      "vol_bin": "high",
      "side_leading": "up_leading",
      "abs_d_bps_min": 2,
      "abs_d_bps_max": 4,
      "sample_count": 1418,
      "wins": 793,
      "p_win": 0.559238,
      "p_win_lower": 0.537459
    },
    {
      "remaining_sec": 180,
      "vol_bin": "high",
      "side_leading": "up_leading",
      "abs_d_bps_min": 4,
      "abs_d_bps_max": 6,
      "sample_count": 1362,
      "wins": 824,
      "p_win": 0.604993,
      "p_win_lower": 0.583017
    },
    {
      "remaining_sec": 180,
      "vol_bin": "high",
      "side_leading": "up_leading",
      "abs_d_bps_min": 6,
      "abs_d_bps_max": 8,
      "sample_count": 1228,
      "wins": 791,
      "p_win": 0.644137,
      "p_win_lower": 0.621369
    },
    {
      "remaining_sec": 180,
      "vol_bin": "high",
      "side_leading": "up_leading",
      "abs_d_bps_min": 8,
      "abs_d_bps_max": 10,
      "sample_count": 1084,
      "wins": 723,
      "p_win": 0.666974,
      "p_win_lower": 0.643038
    },
    {
      "remaining_sec": 180,
      "vol_bin": "high",
      "side_leading": "up_leading",
      "abs_d_bps_min": 10,
      "abs_d_bps_max": 15,
      "sample_count": 2122,
      "wins": 1581,
      "p_win": 0.745052,
      "p_win_lower": 0.729184
    },
    {
      "remaining_sec": 180,
      "vol_bin": "high",
      "side_leading": "up_leading",
      "abs_d_bps_min": 15,
      "abs_d_bps_max": 20,
      "sample_count": 1464,
      "wins": 1213,
      "p_win": 0.828552,
      "p_win_lower": 0.811746
    },
    {
      "remaining_sec": 180,
      "vol_bin": "high",
      "side_leading": "up_leading",
      "abs_d_bps_min": 20,
      "abs_d_bps_max": 25,
      "sample_count": 938,
      "wins": 818,
      "p_win": 0.872068,
      "p_win_lower": 0.853053
    },
    {
      "remaining_sec": 180,
      "vol_bin": "high",
      "side_leading": "up_leading",
      "abs_d_bps_min": 25,
      "abs_d_bps_max": 30,
      "sample_count": 573,
      "wins": 521,
      "p_win": 0.90925,
      "p_win_lower": 0.88754
    },
    {
      "remaining_sec": 180,
      "vol_bin": "high",
      "side_leading": "up_leading",
      "abs_d_bps_min": 30,
      "abs_d_bps_max": 40,
      "sample_count": 517,
      "wins": 483,
      "p_win": 0.934236,
      "p_win_lower": 0.913948
    },
    {
      "remaining_sec": 180,
      "vol_bin": "high",
      "side_leading": "down_leading",
      "abs_d_bps_min": 0,
      "abs_d_bps_max": 2,
      "sample_count": 714,
      "wins": 378,
      "p_win": 0.529412,
      "p_win_lower": 0.498632
    },
    {
      "remaining_sec": 180,
      "vol_bin": "high",
      "side_leading": "down_leading",
      "abs_d_bps_min": 2,
      "abs_d_bps_max": 4,
      "sample_count": 1372,
      "wins": 787,
      "p_win": 0.573615,
      "p_win_lower": 0.551529
    },
    {
      "remaining_sec": 180,
      "vol_bin": "high",
      "side_leading": "down_leading",
      "abs_d_bps_min": 4,
      "abs_d_bps_max": 6,
      "sample_count": 1437,
      "wins": 902,
      "p_win": 0.627697,
      "p_win_lower": 0.606498
    },
    {
      "remaining_sec": 180,
      "vol_bin": "high",
      "side_leading": "down_leading",
      "abs_d_bps_min": 6,
      "abs_d_bps_max": 8,
      "sample_count": 1189,
      "wins": 767,
      "p_win": 0.64508,
      "p_win_lower": 0.621949
    },
    {
      "remaining_sec": 180,
      "vol_bin": "high",
      "side_leading": "down_leading",
      "abs_d_bps_min": 8,
      "abs_d_bps_max": 10,
      "sample_count": 1077,
      "wins": 730,
      "p_win": 0.677809,
      "p_win_lower": 0.653965
    },
    {
      "remaining_sec": 180,
      "vol_bin": "high",
      "side_leading": "down_leading",
      "abs_d_bps_min": 10,
      "abs_d_bps_max": 15,
      "sample_count": 2179,
      "wins": 1628,
      "p_win": 0.747132,
      "p_win_lower": 0.731515
    },
    {
      "remaining_sec": 180,
      "vol_bin": "high",
      "side_leading": "down_leading",
      "abs_d_bps_min": 15,
      "abs_d_bps_max": 20,
      "sample_count": 1424,
      "wins": 1157,
      "p_win": 0.8125,
      "p_win_lower": 0.7949
    },
    {
      "remaining_sec": 180,
      "vol_bin": "high",
      "side_leading": "down_leading",
      "abs_d_bps_min": 20,
      "abs_d_bps_max": 25,
      "sample_count": 912,
      "wins": 776,
      "p_win": 0.850877,
      "p_win_lower": 0.830438
    },
    {
      "remaining_sec": 180,
      "vol_bin": "high",
      "side_leading": "down_leading",
      "abs_d_bps_min": 25,
      "abs_d_bps_max": 30,
      "sample_count": 582,
      "wins": 523,
      "p_win": 0.898625,
      "p_win_lower": 0.876166
    },
    {
      "remaining_sec": 180,
      "vol_bin": "high",
      "side_leading": "down_leading",
      "abs_d_bps_min": 30,
      "abs_d_bps_max": 40,
      "sample_count": 524,
      "wins": 493,
      "p_win": 0.94084,
      "p_win_lower": 0.921515
    },
    {
      "remaining_sec": 180,
      "vol_bin": "extreme",
      "side_leading": "up_leading",
      "abs_d_bps_min": 10,
      "abs_d_bps_max": 15,
      "sample_count": 799,
      "wins": 550,
      "p_win": 0.68836,
      "p_win_lower": 0.66081
    },
    {
      "remaining_sec": 180,
      "vol_bin": "extreme",
      "side_leading": "up_leading",
      "abs_d_bps_min": 15,
      "abs_d_bps_max": 20,
      "sample_count": 638,
      "wins": 459,
      "p_win": 0.719436,
      "p_win_lower": 0.689298
    },
    {
      "remaining_sec": 180,
      "vol_bin": "extreme",
      "side_leading": "up_leading",
      "abs_d_bps_min": 20,
      "abs_d_bps_max": 25,
      "sample_count": 531,
      "wins": 419,
      "p_win": 0.789077,
      "p_win_lower": 0.758527
    },
    {
      "remaining_sec": 180,
      "vol_bin": "extreme",
      "side_leading": "down_leading",
      "abs_d_bps_min": 10,
      "abs_d_bps_max": 15,
      "sample_count": 738,
      "wins": 493,
      "p_win": 0.668022,
      "p_win_lower": 0.638939
    },
    {
      "remaining_sec": 180,
      "vol_bin": "extreme",
      "side_leading": "down_leading",
      "abs_d_bps_min": 15,
      "abs_d_bps_max": 20,
      "sample_count": 584,
      "wins": 421,
      "p_win": 0.72089,
      "p_win_lower": 0.689393
    },
    {
      "remaining_sec": 240,
      "vol_bin": "low",
      "side_leading": "up_leading",
      "abs_d_bps_min": 0,
      "abs_d_bps_max": 2,
      "sample_count": 3595,
      "wins": 1966,
      "p_win": 0.546871,
      "p_win_lower": 0.533184
    },
    {
      "remaining_sec": 240,
      "vol_bin": "low",
      "side_leading": "up_leading",
      "abs_d_bps_min": 2,
      "abs_d_bps_max": 4,
      "sample_count": 5366,
      "wins": 3328,
      "p_win": 0.620201,
      "p_win_lower": 0.609245
    },
    {
      "remaining_sec": 240,
      "vol_bin": "low",
      "side_leading": "up_leading",
      "abs_d_bps_min": 4,
      "abs_d_bps_max": 6,
      "sample_count": 3195,
      "wins": 2227,
      "p_win": 0.697027,
      "p_win_lower": 0.683491
    },
    {
      "remaining_sec": 240,
      "vol_bin": "low",
      "side_leading": "up_leading",
      "abs_d_bps_min": 6,
      "abs_d_bps_max": 8,
      "sample_count": 1664,
      "wins": 1255,
      "p_win": 0.754207,
      "p_win_lower": 0.736442
    },
    {
      "remaining_sec": 240,
      "vol_bin": "low",
      "side_leading": "up_leading",
      "abs_d_bps_min": 8,
      "abs_d_bps_max": 10,
      "sample_count": 807,
      "wins": 656,
      "p_win": 0.812887,
      "p_win_lower": 0.789273
    },
    {
      "remaining_sec": 240,
      "vol_bin": "low",
      "side_leading": "up_leading",
      "abs_d_bps_min": 10,
      "abs_d_bps_max": 15,
      "sample_count": 728,
      "wins": 609,
      "p_win": 0.836538,
      "p_win_lower": 0.812756
    },
    {
      "remaining_sec": 240,
      "vol_bin": "low",
      "side_leading": "down_leading",
      "abs_d_bps_min": 0,
      "abs_d_bps_max": 2,
      "sample_count": 3576,
      "wins": 2003,
      "p_win": 0.560123,
      "p_win_lower": 0.546429
    },
    {
      "remaining_sec": 240,
      "vol_bin": "low",
      "side_leading": "down_leading",
      "abs_d_bps_min": 2,
      "abs_d_bps_max": 4,
      "sample_count": 5192,
      "wins": 3249,
      "p_win": 0.62577,
      "p_win_lower": 0.61466
    },
    {
      "remaining_sec": 240,
      "vol_bin": "low",
      "side_leading": "down_leading",
      "abs_d_bps_min": 4,
      "abs_d_bps_max": 6,
      "sample_count": 3074,
      "wins": 2201,
      "p_win": 0.716005,
      "p_win_lower": 0.702441
    },
    {
      "remaining_sec": 240,
      "vol_bin": "low",
      "side_leading": "down_leading",
      "abs_d_bps_min": 6,
      "abs_d_bps_max": 8,
      "sample_count": 1652,
      "wins": 1234,
      "p_win": 0.746973,
      "p_win_lower": 0.728985
    },
    {
      "remaining_sec": 240,
      "vol_bin": "low",
      "side_leading": "down_leading",
      "abs_d_bps_min": 8,
      "abs_d_bps_max": 10,
      "sample_count": 868,
      "wins": 714,
      "p_win": 0.822581,
      "p_win_lower": 0.800259
    },
    {
      "remaining_sec": 240,
      "vol_bin": "low",
      "side_leading": "down_leading",
      "abs_d_bps_min": 10,
      "abs_d_bps_max": 15,
      "sample_count": 773,
      "wins": 670,
      "p_win": 0.866753,
      "p_win_lower": 0.845362
    },
    {
      "remaining_sec": 240,
      "vol_bin": "normal",
      "side_leading": "up_leading",
      "abs_d_bps_min": 0,
      "abs_d_bps_max": 2,
      "sample_count": 2335,
      "wins": 1275,
      "p_win": 0.546039,
      "p_win_lower": 0.529047
    },
    {
      "remaining_sec": 240,
      "vol_bin": "normal",
      "side_leading": "up_leading",
      "abs_d_bps_min": 2,
      "abs_d_bps_max": 4,
      "sample_count": 4303,
      "wins": 2480,
      "p_win": 0.576342,
      "p_win_lower": 0.563907
    },
    {
      "remaining_sec": 240,
      "vol_bin": "normal",
      "side_leading": "up_leading",
      "abs_d_bps_min": 4,
      "abs_d_bps_max": 6,
      "sample_count": 3387,
      "wins": 2185,
      "p_win": 0.645114,
      "p_win_lower": 0.631479
    },
    {
      "remaining_sec": 240,
      "vol_bin": "normal",
      "side_leading": "up_leading",
      "abs_d_bps_min": 6,
      "abs_d_bps_max": 8,
      "sample_count": 2399,
      "wins": 1643,
      "p_win": 0.684869,
      "p_win_lower": 0.669066
    },
    {
      "remaining_sec": 240,
      "vol_bin": "normal",
      "side_leading": "up_leading",
      "abs_d_bps_min": 8,
      "abs_d_bps_max": 10,
      "sample_count": 1557,
      "wins": 1166,
      "p_win": 0.748876,
      "p_win_lower": 0.730377
    },
    {
      "remaining_sec": 240,
      "vol_bin": "normal",
      "side_leading": "up_leading",
      "abs_d_bps_min": 10,
      "abs_d_bps_max": 15,
      "sample_count": 1884,
      "wins": 1505,
      "p_win": 0.798832,
      "p_win_lower": 0.783217
    },
    {
      "remaining_sec": 240,
      "vol_bin": "normal",
      "side_leading": "up_leading",
      "abs_d_bps_min": 15,
      "abs_d_bps_max": 20,
      "sample_count": 544,
      "wins": 466,
      "p_win": 0.856618,
      "p_win_lower": 0.830135
    },
    {
      "remaining_sec": 240,
      "vol_bin": "normal",
      "side_leading": "down_leading",
      "abs_d_bps_min": 0,
      "abs_d_bps_max": 2,
      "sample_count": 2412,
      "wins": 1293,
      "p_win": 0.53607,
      "p_win_lower": 0.519336
    },
    {
      "remaining_sec": 240,
      "vol_bin": "normal",
      "side_leading": "down_leading",
      "abs_d_bps_min": 2,
      "abs_d_bps_max": 4,
      "sample_count": 4258,
      "wins": 2482,
      "p_win": 0.582903,
      "p_win_lower": 0.570424
    },
    {
      "remaining_sec": 240,
      "vol_bin": "normal",
      "side_leading": "down_leading",
      "abs_d_bps_min": 4,
      "abs_d_bps_max": 6,
      "sample_count": 3268,
      "wins": 2117,
      "p_win": 0.647797,
      "p_win_lower": 0.633936
    },
    {
      "remaining_sec": 240,
      "vol_bin": "normal",
      "side_leading": "down_leading",
      "abs_d_bps_min": 6,
      "abs_d_bps_max": 8,
      "sample_count": 2321,
      "wins": 1667,
      "p_win": 0.718225,
      "p_win_lower": 0.702618
    },
    {
      "remaining_sec": 240,
      "vol_bin": "normal",
      "side_leading": "down_leading",
      "abs_d_bps_min": 8,
      "abs_d_bps_max": 10,
      "sample_count": 1537,
      "wins": 1137,
      "p_win": 0.739753,
      "p_win_lower": 0.720933
    },
    {
      "remaining_sec": 240,
      "vol_bin": "normal",
      "side_leading": "down_leading",
      "abs_d_bps_min": 10,
      "abs_d_bps_max": 15,
      "sample_count": 1889,
      "wins": 1489,
      "p_win": 0.788248,
      "p_win_lower": 0.772379
    },
    {
      "remaining_sec": 240,
      "vol_bin": "normal",
      "side_leading": "down_leading",
      "abs_d_bps_min": 15,
      "abs_d_bps_max": 20,
      "sample_count": 579,
      "wins": 487,
      "p_win": 0.841105,
      "p_win_lower": 0.814536
    },
    {
      "remaining_sec": 240,
      "vol_bin": "high",
      "side_leading": "up_leading",
      "abs_d_bps_min": 0,
      "abs_d_bps_max": 2,
      "sample_count": 1173,
      "wins": 595,
      "p_win": 0.507246,
      "p_win_lower": 0.483246
    },
    {
      "remaining_sec": 240,
      "vol_bin": "high",
      "side_leading": "up_leading",
      "abs_d_bps_min": 2,
      "abs_d_bps_max": 4,
      "sample_count": 2138,
      "wins": 1216,
      "p_win": 0.568756,
      "p_win_lower": 0.551062
    },
    {
      "remaining_sec": 240,
      "vol_bin": "high",
      "side_leading": "up_leading",
      "abs_d_bps_min": 4,
      "abs_d_bps_max": 6,
      "sample_count": 1924,
      "wins": 1157,
      "p_win": 0.601351,
      "p_win_lower": 0.58286
    },
    {
      "remaining_sec": 240,
      "vol_bin": "high",
      "side_leading": "up_leading",
      "abs_d_bps_min": 6,
      "abs_d_bps_max": 8,
      "sample_count": 1562,
      "wins": 1004,
      "p_win": 0.642766,
      "p_win_lower": 0.622591
    },
    {
      "remaining_sec": 240,
      "vol_bin": "high",
      "side_leading": "up_leading",
      "abs_d_bps_min": 8,
      "abs_d_bps_max": 10,
      "sample_count": 1236,
      "wins": 844,
      "p_win": 0.682848,
      "p_win_lower": 0.660695
    },
    {
      "remaining_sec": 240,
      "vol_bin": "high",
      "side_leading": "up_leading",
      "abs_d_bps_min": 10,
      "abs_d_bps_max": 15,
      "sample_count": 1956,
      "wins": 1402,
      "p_win": 0.716769,
      "p_win_lower": 0.699721
    },
    {
      "remaining_sec": 240,
      "vol_bin": "high",
      "side_leading": "up_leading",
      "abs_d_bps_min": 15,
      "abs_d_bps_max": 20,
      "sample_count": 884,
      "wins": 704,
      "p_win": 0.79638,
      "p_win_lower": 0.773213
    },
    {
      "remaining_sec": 240,
      "vol_bin": "high",
      "side_leading": "down_leading",
      "abs_d_bps_min": 0,
      "abs_d_bps_max": 2,
      "sample_count": 1109,
      "wins": 616,
      "p_win": 0.555455,
      "p_win_lower": 0.530805
    },
    {
      "remaining_sec": 240,
      "vol_bin": "high",
      "side_leading": "down_leading",
      "abs_d_bps_min": 2,
      "abs_d_bps_max": 4,
      "sample_count": 2208,
      "wins": 1253,
      "p_win": 0.567482,
      "p_win_lower": 0.550067
    },
    {
      "remaining_sec": 240,
      "vol_bin": "high",
      "side_leading": "down_leading",
      "abs_d_bps_min": 4,
      "abs_d_bps_max": 6,
      "sample_count": 1828,
      "wins": 1116,
      "p_win": 0.610503,
      "p_win_lower": 0.591592
    },
    {
      "remaining_sec": 240,
      "vol_bin": "high",
      "side_leading": "down_leading",
      "abs_d_bps_min": 6,
      "abs_d_bps_max": 8,
      "sample_count": 1514,
      "wins": 987,
      "p_win": 0.651915,
      "p_win_lower": 0.631523
    },
    {
      "remaining_sec": 240,
      "vol_bin": "high",
      "side_leading": "down_leading",
      "abs_d_bps_min": 8,
      "abs_d_bps_max": 10,
      "sample_count": 1237,
      "wins": 815,
      "p_win": 0.658852,
      "p_win_lower": 0.636354
    },
    {
      "remaining_sec": 240,
      "vol_bin": "high",
      "side_leading": "down_leading",
      "abs_d_bps_min": 10,
      "abs_d_bps_max": 15,
      "sample_count": 1914,
      "wins": 1417,
      "p_win": 0.740334,
      "p_win_lower": 0.723518
    },
    {
      "remaining_sec": 240,
      "vol_bin": "high",
      "side_leading": "down_leading",
      "abs_d_bps_min": 15,
      "abs_d_bps_max": 20,
      "sample_count": 889,
      "wins": 711,
      "p_win": 0.799775,
      "p_win_lower": 0.776804
    },
    {
      "remaining_sec": 240,
      "vol_bin": "extreme",
      "side_leading": "up_leading",
      "abs_d_bps_min": 2,
      "abs_d_bps_max": 4,
      "sample_count": 648,
      "wins": 351,
      "p_win": 0.541667,
      "p_win_lower": 0.509363
    },
    {
      "remaining_sec": 240,
      "vol_bin": "extreme",
      "side_leading": "up_leading",
      "abs_d_bps_min": 4,
      "abs_d_bps_max": 6,
      "sample_count": 613,
      "wins": 369,
      "p_win": 0.601958,
      "p_win_lower": 0.569058
    },
    {
      "remaining_sec": 240,
      "vol_bin": "extreme",
      "side_leading": "up_leading",
      "abs_d_bps_min": 6,
      "abs_d_bps_max": 8,
      "sample_count": 550,
      "wins": 343,
      "p_win": 0.623636,
      "p_win_lower": 0.589129
    },
    {
      "remaining_sec": 240,
      "vol_bin": "extreme",
      "side_leading": "up_leading",
      "abs_d_bps_min": 10,
      "abs_d_bps_max": 15,
      "sample_count": 931,
      "wins": 619,
      "p_win": 0.664876,
      "p_win_lower": 0.638984
    },
    {
      "remaining_sec": 240,
      "vol_bin": "extreme",
      "side_leading": "up_leading",
      "abs_d_bps_min": 15,
      "abs_d_bps_max": 20,
      "sample_count": 595,
      "wins": 432,
      "p_win": 0.72605,
      "p_win_lower": 0.695003
    },
    {
      "remaining_sec": 240,
      "vol_bin": "extreme",
      "side_leading": "down_leading",
      "abs_d_bps_min": 2,
      "abs_d_bps_max": 4,
      "sample_count": 592,
      "wins": 320,
      "p_win": 0.540541,
      "p_win_lower": 0.506741
    },
    {
      "remaining_sec": 240,
      "vol_bin": "extreme",
      "side_leading": "down_leading",
      "abs_d_bps_min": 4,
      "abs_d_bps_max": 6,
      "sample_count": 540,
      "wins": 313,
      "p_win": 0.57963,
      "p_win_lower": 0.544377
    },
    {
      "remaining_sec": 240,
      "vol_bin": "extreme",
      "side_leading": "down_leading",
      "abs_d_bps_min": 6,
      "abs_d_bps_max": 8,
      "sample_count": 506,
      "wins": 293,
      "p_win": 0.579051,
      "p_win_lower": 0.542622
    },
    {
      "remaining_sec": 240,
      "vol_bin": "extreme",
      "side_leading": "down_leading",
      "abs_d_bps_min": 10,
      "abs_d_bps_max": 15,
      "sample_count": 907,
      "wins": 593,
      "p_win": 0.653804,
      "p_win_lower": 0.627396
    },
    {
      "remaining_sec": 240,
      "vol_bin": "extreme",
      "side_leading": "down_leading",
      "abs_d_bps_min": 15,
      "abs_d_bps_max": 20,
      "sample_count": 592,
      "wins": 424,
      "p_win": 0.716216,
      "p_win_lower": 0.684807
    }
  ],
  "runtime_config_hash": "256ce3867593f72c1f7532377b57212588d9851b08262f19b23f77998afa2f3c"
}
